nsrt_mk3_dev/__init__.py
nsrt_mk3_dev/nsrt_mk3_dev.py
nsrt_mk3_dev/version.py
nsrt_mk3_dev-1.0.0.dist-info/LICENSE.txt
nsrt_mk3_dev-1.0.0.dist-info/METADATA
nsrt_mk3_dev-1.0.0.dist-info/WHEEL
nsrt_mk3_dev-1.0.0.dist-info/top_level.txt
nsrt_mk3_dev-1.0.0.dist-info/RECORD
