Metadata-Version: 2.1
Name: nsrt-mk3-dev
Version: 1.0.0
Summary: NSRT MK3 Dev Sound Level Meter
Home-page: https://xanderhendriks.github.io/nsrt-mk3-dev
Author: Xander Hendriks
Author-email: xander.hendriks@nx-solutions.com
License: UNKNOWN
Project-URL: Bug Reports, https://github.com/xanderhendriks/nsrt-mk3-dev/issues
Project-URL: Source, https://github.com/xanderhendriks/nsrt-mk3-dev
Platform: UNKNOWN
Classifier: Programming Language :: Python :: 3
Classifier: License :: OSI Approved :: MIT License
Classifier: Programming Language :: Python :: 3 :: Only
Requires-Python: >=3.6
Requires-Dist: pyserial
Provides-Extra: dev
Requires-Dist: check-manifest ; extra == 'dev'
Requires-Dist: flake8 ; extra == 'dev'
Provides-Extra: doc
Requires-Dist: sphinx ; extra == 'doc'
Requires-Dist: sphinx-rtd-theme ; extra == 'doc'
Provides-Extra: test
Requires-Dist: pytest ; extra == 'test'
